zModules/__init__.py
zModules/zBanner/__init__.py
zModules/zBanner/banner.py
zModules/zBanner/colors.py
zModules/zBanner/fonts.py
zModules/zBanner/recolor_horizontal.py
zModules/zBanner/recolor_vertical.py
zModules/zCryptography/__init__.py
zModules/zCryptography/cryptography.py
zModules/zCtk/__init__.py
zModules/zCtk/extensions.py
zModules/zCtk/zctk.py
zModules/zDatabase/__init__.py
zModules/zDatabase/sql.py
zModules/zExtensions/__init__.py
zModules/zExtensions/pp.py
zModules/zNetwork/HTTP_Response_Status_Codes.py
zModules/zNetwork/__init__.py
zModules/zNetwork/network_devices.py
zModules/zNetwork/router_ip.py
zModules/zOs/__init__.py
zModules/zOs/utils.py
zmodule-1.0.8.dist-info/METADATA
zmodule-1.0.8.dist-info/WHEEL
zmodule-1.0.8.dist-info/top_level.txt
zmodule-1.0.8.dist-info/RECORD
