Metadata-Version: 2.4
Name: zModule
Version: 1.0.8
Summary: Just some Modules.
Author: zisia13
Author-email: nothing@nothing.com
Classifier: Programming Language :: Python :: 3
Classifier: License :: OSI Approved :: MIT License
Dynamic: author
Dynamic: author-email
Dynamic: classifier
Dynamic: summary
